EasyOIDC/__init__.py
EasyOIDC/auth.py
EasyOIDC/config.py
EasyOIDC/session.py
EasyOIDC/utils.py
EasyOIDC/frameworks/__init__.py
EasyOIDC/frameworks/flask.py
EasyOIDC/frameworks/nicegui.py
EasyOIDC/frameworks/streamlit.py
EasyOIDC/frameworks/taipy.py
easyoidc-0.1.12.dist-info/METADATA
easyoidc-0.1.12.dist-info/WHEEL
easyoidc-0.1.12.dist-info/licenses/LICENSE
easyoidc-0.1.12.dist-info/RECORD
