Metadata-Version: 2.4
Name: EasyOIDC
Version: 0.1.12
Summary: Easy integration with OIDC authentication servers
Project-URL: Homepage, https://github.com/jpmanson/EasyOIDC
Project-URL: Repository, https://github.com/jpmanson/EasyOIDC
Project-URL: Issues, https://github.com/jpmanson/EasyOIDC/issues
Author-email: Juan Pablo Manson <jpmanson@gmail.com>
License: MIT License
License-File: LICENSE
Keywords: authentication,oauth,oidc,openid-connect
Classifier: Development Status :: 4 - Beta
Classifier: Intended Audience :: Developers
Classifier: Programming Language :: Python :: 3
Classifier: Programming Language :: Python :: 3.9
Classifier: Programming Language :: Python :: 3.10
Classifier: Programming Language :: Python :: 3.11
Classifier: Programming Language :: Python :: 3.12
Requires-Python: >=3.9
Requires-Dist: authlib>=1.3.0
Requires-Dist: python-decouple>=3.8
Requires-Dist: redis-collections>=0.12.0
Requires-Dist: requests>=2.31.0
Provides-Extra: dev
Requires-Dist: pytest; extra == 'dev'
Requires-Dist: ruff; extra == 'dev'
Provides-Extra: flask
Requires-Dist: flask>=2.3.3; extra == 'flask'
Provides-Extra: nicegui
Requires-Dist: fastapi; extra == 'nicegui'
Requires-Dist: nicegui>=1.4.0; extra == 'nicegui'
Provides-Extra: taipy
Requires-Dist: taipy>=2.4.0; extra == 'taipy'
